storjkademlia-0.7.4.dist-info/DESCRIPTION.rst
storjkademlia-0.7.4.dist-info/metadata.json
storjkademlia-0.7.4.dist-info/METADATA
storjkademlia-0.7.4.dist-info/WHEEL
storjkademlia-0.7.4.dist-info/top_level.txt
storjkademlia-0.7.4.dist-info/RECORD
storjkademlia/crawling.py
storjkademlia/__init__.py
storjkademlia/log.py
storjkademlia/utils.py
storjkademlia/storage.py
storjkademlia/network.py
storjkademlia/node.py
storjkademlia/protocol.py
storjkademlia/routing.py
storjkademlia/tests/test_swarm.py
storjkademlia/tests/test_routing.py
storjkademlia/tests/__init__.py
storjkademlia/tests/utils.py
storjkademlia/tests/test_node.py
storjkademlia/tests/test_utils.py
kademlia/crawling.py
kademlia/__init__.py
kademlia/log.py
kademlia/utils.py
kademlia/storage.py
kademlia/network.py
kademlia/node.py
kademlia/protocol.py
kademlia/routing.py
kademlia/tests/test_swarm.py
kademlia/tests/test_routing.py
kademlia/tests/__init__.py
kademlia/tests/utils.py
kademlia/tests/test_node.py
kademlia/tests/test_utils.py
