Metadata-Version: 2.0
Name: storjkademlia
Version: 0.7.4
Summary: Kademlia is a distributed hash table for decentralized peer-to-peer computer networks.
Home-page: https://github.com/Storj/storjkademlia
Author: Brian Muller
Author-email: bamuller@gmail.com
License: MIT
Platform: UNKNOWN
Classifier: Development Status :: 5 - Production/Stable
Classifier: Intended Audience :: Developers
Classifier: License :: OSI Approved :: MIT License
Classifier: Operating System :: OS Independent
Classifier: Programming Language :: Python
Classifier: Programming Language :: Python :: 2
Classifier: Programming Language :: Python :: 2.7
Classifier: Programming Language :: Python :: 3
Classifier: Programming Language :: Python :: 3.3
Classifier: Programming Language :: Python :: 3.4
Classifier: Programming Language :: Python :: 3.5
Classifier: Topic :: Software Development :: Libraries :: Python Modules
Requires-Dist: Twisted (>=15.5.0)
Requires-Dist: storjrpcudp (>=2.0)
Requires-Dist: future (>=0.15.2)
